{
  "parent": "minecraft:recipes/root",
  "criteria": {
    "has_ingredient": {
      "trigger": "minecraft:inventory_changed",
      "conditions": {
        "items": [
          {
            "items": "got:basalt_rock"
          }
        ]
      }
    },
    "has_the_recipe": {
      "trigger": "minecraft:recipe_unlocked",
      "conditions": {
        "recipe": "got:basalt_rock_slab_recipe"
      }
    }
  },
  "requirements": [
    [
      "has_ingredient",
      "has_the_recipe"
    ]
  ],
  "rewards": {
    "recipes": [
      "got:basalt_rock_slab_recipe"
    ]
  }
}